Metadata-Version: 2.1
Name: MailGun-V3
Version: 0.3.2
Summary: Python Wrapper With Fluent API for Mailgun v3
Home-page: https://github.com/martin-majlis/MailGunV3
Author: Martin Majlis
Author-email: martin@majlis.cz
License: MIT
Download-URL: https://github.com/martin-majlis/MailGunV3/archive/master.tar.gz
Keywords: mailgun mail
Platform: any
Classifier: Development Status :: 4 - Beta
Classifier: Environment :: Web Environment
Classifier: Intended Audience :: Developers
Classifier: Programming Language :: Python
Classifier: Programming Language :: Python :: 3
Classifier: License :: OSI Approved :: MIT License
Classifier: Operating System :: OS Independent
Classifier: Topic :: Communications :: Email
Classifier: Topic :: Software Development :: Libraries :: Python Modules
Provides-Extra: testing
